beancount_fava_mcp/__init__.py
beancount_fava_mcp/main.py
beancount_fava_mcp/server.py
beancount_fava_mcp-0.1.1.dist-info/METADATA
beancount_fava_mcp-0.1.1.dist-info/WHEEL
beancount_fava_mcp-0.1.1.dist-info/entry_points.txt
beancount_fava_mcp-0.1.1.dist-info/licenses/LICENSE
beancount_fava_mcp-0.1.1.dist-info/RECORD
