Metadata-Version: 2.4
Name: beancount-fava-mcp
Version: 0.1.1
Summary: MCP server for Beancount Fava
License-File: LICENSE
Requires-Python: >=3.10
Requires-Dist: mcp
Requires-Dist: python-dotenv
Requires-Dist: requests
